Metadata-Version: 2.1
Name: autofeather-dash
Version: 2.14.2.1
Summary: A Python framework for building reactive web-apps. Developed by Plotly.
Home-page: https://plotly.com/dash
Author: Autofeather
Author-email: lxstr@protonmail.ch
License: MIT
Project-URL: Documentation, https://dash.plotly.com
Project-URL: Source, https://github.com/plotly/dash
Project-URL: Issue Tracker, https://github.com/plotly/dash/issues
Classifier: Development Status :: 5 - Production/Stable
Classifier: Environment :: Web Environment
Classifier: Framework :: Dash
Classifier: Framework :: Flask
Classifier: Intended Audience :: Developers
Classifier: Intended Audience :: Education
Classifier: Intended Audience :: Financial and Insurance Industry
Classifier: Intended Audience :: Healthcare Industry
Classifier: Intended Audience :: Manufacturing
Classifier: Intended Audience :: Science/Research
Classifier: License :: OSI Approved :: MIT License
Classifier: Programming Language :: Python
Classifier: Programming Language :: Python :: 3
Classifier: Programming Language :: Python :: 3.6
Classifier: Programming Language :: Python :: 3.7
Classifier: Programming Language :: Python :: 3.8
Classifier: Programming Language :: Python :: 3.9
Classifier: Topic :: Database :: Front-Ends
Classifier: Topic :: Office/Business :: Financial :: Spreadsheet
Classifier: Topic :: Scientific/Engineering :: Visualization
Classifier: Topic :: Software Development :: Libraries :: Application Frameworks
Classifier: Topic :: Software Development :: Widget Sets
Requires-Python: >=3.6
License-File: LICENSE
Requires-Dist: Flask <3.1,>=1.0.4
Requires-Dist: Werkzeug <3.1
Requires-Dist: plotly >=5.0.0
Requires-Dist: dash-html-components ==2.0.0
Requires-Dist: dash-core-components ==2.0.0
Requires-Dist: dash-table ==5.0.0
Requires-Dist: typing-extensions >=4.1.1
Requires-Dist: requests
Requires-Dist: retrying
Requires-Dist: ansi2html
Requires-Dist: nest-asyncio
Requires-Dist: setuptools
Requires-Dist: importlib-metadata ==4.8.3 ; python_version < "3.7"
Requires-Dist: contextvars ==2.4 ; python_version < "3.7"
Requires-Dist: importlib-metadata ; python_version >= "3.7"
Provides-Extra: celery
Requires-Dist: redis >=3.5.3 ; extra == 'celery'
Requires-Dist: celery[redis] >=5.1.2 ; extra == 'celery'
Requires-Dist: importlib-metadata <5 ; (python_version < "3.8") and extra == 'celery'
Provides-Extra: ci
Requires-Dist: dash-flow-example ==0.0.5 ; extra == 'ci'
Requires-Dist: dash-dangerously-set-inner-html ; extra == 'ci'
Requires-Dist: flake8 ==3.9.2 ; extra == 'ci'
Requires-Dist: flaky ==3.7.0 ; extra == 'ci'
Requires-Dist: flask-talisman ==1.0.0 ; extra == 'ci'
Requires-Dist: mimesis ; extra == 'ci'
Requires-Dist: mock ==4.0.3 ; extra == 'ci'
Requires-Dist: numpy <=1.25.2 ; extra == 'ci'
Requires-Dist: preconditions ; extra == 'ci'
Requires-Dist: pylint ==2.13.5 ; extra == 'ci'
Requires-Dist: pytest-mock ; extra == 'ci'
Requires-Dist: pytest-sugar ==0.9.6 ; extra == 'ci'
Requires-Dist: pytest-rerunfailures ; extra == 'ci'
Requires-Dist: jupyterlab <4.0.0 ; extra == 'ci'
Requires-Dist: black ==21.6b0 ; (python_version < "3.7") and extra == 'ci'
Requires-Dist: isort ==4.3.21 ; (python_version < "3.7") and extra == 'ci'
Requires-Dist: orjson ==3.5.4 ; (python_version < "3.7") and extra == 'ci'
Requires-Dist: pyarrow <3 ; (python_version < "3.7") and extra == 'ci'
Requires-Dist: pandas ==1.1.5 ; (python_version < "3.8") and extra == 'ci'
Requires-Dist: xlrd <2 ; (python_version < "3.8") and extra == 'ci'
Requires-Dist: black ==22.3.0 ; (python_version >= "3.7") and extra == 'ci'
Requires-Dist: orjson ==3.6.7 ; (python_version >= "3.7") and extra == 'ci'
Requires-Dist: pyarrow ; (python_version >= "3.7") and extra == 'ci'
Requires-Dist: openpyxl ; (python_version >= "3.8") and extra == 'ci'
Requires-Dist: pandas >=1.4.0 ; (python_version >= "3.8") and extra == 'ci'
Requires-Dist: xlrd >=2.0.1 ; (python_version >= "3.8") and extra == 'ci'
Provides-Extra: compress
Requires-Dist: flask-compress ; extra == 'compress'
Provides-Extra: dev
Requires-Dist: coloredlogs >=15.0.1 ; extra == 'dev'
Requires-Dist: fire >=0.4.0 ; extra == 'dev'
Requires-Dist: PyYAML >=5.4.1 ; extra == 'dev'
Provides-Extra: diskcache
Requires-Dist: diskcache >=5.2.1 ; extra == 'diskcache'
Requires-Dist: multiprocess >=0.70.12 ; extra == 'diskcache'
Requires-Dist: psutil >=5.8.0 ; extra == 'diskcache'
Provides-Extra: testing
Requires-Dist: beautifulsoup4 >=4.8.2 ; extra == 'testing'
Requires-Dist: lxml >=4.6.2 ; extra == 'testing'
Requires-Dist: percy >=2.0.2 ; extra == 'testing'
Requires-Dist: pytest >=6.0.2 ; extra == 'testing'
Requires-Dist: requests[security] >=2.21.0 ; extra == 'testing'
Requires-Dist: selenium <=4.2.0,>=3.141.0 ; extra == 'testing'
Requires-Dist: waitress >=1.4.4 ; extra == 'testing'
Requires-Dist: multiprocess >=0.70.12 ; extra == 'testing'
Requires-Dist: psutil >=5.8.0 ; extra == 'testing'
Requires-Dist: dash-testing-stub >=0.0.2 ; extra == 'testing'
Requires-Dist: cryptography <3.4 ; (python_version < "3.7") and extra == 'testing'
